[{
    "membersOnline":10,
    "zoneId":0,
    "groupName":".....:::::[Ragnarok Empire]:::::.....",
    "timeRemaining":"5 hours and 12 minutes"
  },{
    "membersOnline":10,
    "zoneId":2,
    "groupName":"Seamless Gate",
    "timeRemaining":"3 hours and 11 minutes"
  },{
    "membersOnline":3,
    "zoneId":4,
    "groupName":"The Cat Family",
    "timeRemaining":"1 hours and 27 minutes"
  },{
    "membersOnline":3,
    "zoneId":5,
    "groupName":"The Cat Family",
    "timeRemaining":"4 hours and 55 minutes"
  },{
    "membersOnline":1,
    "zoneId":6,
    "groupName":"sinalfa",
    "timeRemaining":"2 hours and 43 minutes"
  },{
    "membersOnline":1,
    "zoneId":7,
    "groupName":"sinalfa",
    "timeRemaining":"1 hours and 15 minutes"
  },{
    "membersOnline":1,
    "zoneId":8,
    "groupName":"sinalfa",
    "timeRemaining":"1 hours and 12 minutes"
  },{
    "membersOnline":7,
    "zoneId":9,
    "groupName":"Hall of Malevolence",
    "timeRemaining":"0 hours and 36 minutes"
  },{
    "membersOnline":1,
    "zoneId":10,
    "groupName":"sinalfa",
    "timeRemaining":"2 hours and 47 minutes"
  },{
    "membersOnline":7,
    "zoneId":11,
    "groupName":"Hall of Malevolence",
    "timeRemaining":"0 hours and 24 minutes"
  },{
    "membersOnline":2,
    "zoneId":12,
    "groupName":"<27001a>Cat<37001A>ha<47001A>r<57001A>s<67001A>is Empire",
    "timeRemaining":"4 hours and 53 minutes"
  },{
    "membersOnline":3,
    "zoneId":13,
    "groupName":"The Cat Family",
    "timeRemaining":"1 hours and 37 minutes"
  },{
    "membersOnline":3,
    "zoneId":14,
    "groupName":"The Cat Family",
    "timeRemaining":"1 hours and 38 minutes"
  },{
    "membersOnline":3,
    "zoneId":15,
    "groupName":"The Cat Family",
    "timeRemaining":"1 hours and 31 minutes"
  },{
    "membersOnline":7,
    "zoneId":16,
    "groupName":"Hall of Malevolence",
    "timeRemaining":"0 hours and 0 minutes"
  },{
    "membersOnline":1,
    "zoneId":17,
    "groupName":"warriorAngels",
    "timeRemaining":"1 hours and 56 minutes"
  },{
    "membersOnline":10,
    "zoneId":18,
    "groupName":"Seamless Gate",
    "timeRemaining":"0 hours and 42 minutes"
  },{
    "membersOnline":2,
    "zoneId":19,
    "groupName":"Ansuzgardaraiwo",
    "timeRemaining":"5 hours and 11 minutes"
  },{
    "membersOnline":6,
    "zoneId":20,
    "groupName":"Hall of Malevolence",
    "timeRemaining":"0 hours and 17 minutes"
  },{
    "membersOnline":1,
    "zoneId":21,
    "groupName":"sinalfa",
    "timeRemaining":"0 hours and 54 minutes"
  },{
    "membersOnline":2,
    "zoneId":22,
    "groupName":"Ansuzgardaraiwo",
    "timeRemaining":"5 hours and 24 minutes"
  },{
    "membersOnline":1,
    "zoneId":23,
    "groupName":"sinalfa",
    "timeRemaining":"2 hours and 42 minutes"
  },{
    "membersOnline":1,
    "zoneId":24,
    "groupName":"Freestyle GunZ",
    "timeRemaining":"3 hours and 37 minutes"
  },{
    "membersOnline":1,
    "zoneId":25,
    "groupName":"Freestyle GunZ",
    "timeRemaining":"4 hours and 59 minutes"
  },{
    "membersOnline":10,
    "zoneId":26,
    "groupName":"Seamless Gate",
    "timeRemaining":"0 hours and 40 minutes"
  },{
    "membersOnline":1,
    "zoneId":27,
    "groupName":"4FuN",
    "timeRemaining":"1 hours and 6 minutes"
  },{
    "membersOnline":3,
    "zoneId":28,
    "groupName":"The Cat Family",
    "timeRemaining":"5 hours and 6 minutes"
  },{
    "membersOnline":1,
    "zoneId":29,
    "groupName":"Freestyle GunZ",
    "timeRemaining":"4 hours and 59 minutes"
  },{
    "membersOnline":1,
    "zoneId":30,
    "groupName":"Freestyle GunZ",
    "timeRemaining":"3 hours and 36 minutes"
  },{
    "membersOnline":6,
    "zoneId":31,
    "groupName":"Nightmare Empire",
    "timeRemaining":"3 hours and 26 minutes"
  },{
    "membersOnline":6,
    "zoneId":32,
    "groupName":"Nightmare Empire",
    "timeRemaining":"0 hours and 21 minutes"
  },{
    "membersOnline":2,
    "zoneId":33,
    "groupName":"Ansuzgardaraiwo",
    "timeRemaining":"0 hours and 48 minutes"
  },{
    "membersOnline":3,
    "zoneId":34,
    "groupName":"The Cat Family",
    "timeRemaining":"4 hours and 55 minutes"
  },{
    "membersOnline":1,
    "zoneId":35,
    "groupName":"4FuN",
    "timeRemaining":"4 hours and 45 minutes"
  },{
    "membersOnline":1,
    "zoneId":36,
    "groupName":"Ancient Knowledge Stone ",
    "timeRemaining":"5 hours and 49 minutes"
  },{
    "membersOnline":3,
    "zoneId":37,
    "groupName":"The Cat Family",
    "timeRemaining":"5 hours and 15 minutes"
  },{
    "membersOnline":1,
    "zoneId":38,
    "groupName":"sinalfa",
    "timeRemaining":"0 hours and 52 minutes"
  },{
    "membersOnline":0,
    "zoneId":39,
    "timeRemaining":"0 hours and 22 minutes"
  },{
    "membersOnline":1,
    "zoneId":40,
    "groupName":"sinalfa",
    "timeRemaining":"1 hours and 12 minutes"
  },{
    "membersOnline":2,
    "zoneId":41,
    "groupName":"Ansuzgardaraiwo",
    "timeRemaining":"5 hours and 23 minutes"
  },{
    "membersOnline":1,
    "zoneId":42,
    "groupName":"4FuN",
    "timeRemaining":"4 hours and 49 minutes"
  },{
    "membersOnline":10,
    "zoneId":43,
    "groupName":"Seamless Gate",
    "timeRemaining":"0 hours and 26 minutes"
  },{
    "membersOnline":10,
    "zoneId":44,
    "groupName":"Seamless Gate",
    "timeRemaining":"0 hours and 24 minutes"
  },{
    "membersOnline":10,
    "zoneId":45,
    "groupName":"Seamless Gate",
    "timeRemaining":"0 hours and 22 minutes"
  },{
    "membersOnline":1,
    "zoneId":46,
    "groupName":"Freestyle GunZ",
    "timeRemaining":"4 hours and 58 minutes"
  },{
    "membersOnline":5,
    "zoneId":47,
    "groupName":"Hall of Malevolence",
    "timeRemaining":"0 hours and 21 minutes"
  },{
    "membersOnline":0,
    "zoneId":48,
    "timeRemaining":"4 hours and 39 minutes"
  },{
    "membersOnline":6,
    "zoneId":49,
    "groupName":"Nightmare Empire",
    "timeRemaining":"0 hours and 33 minutes"
  },{
    "membersOnline":6,
    "zoneId":50,
    "groupName":"Nightmare Empire",
    "timeRemaining":"3 hours and 31 minutes"
  },{
    "membersOnline":1,
    "zoneId":51,
    "groupName":"sinalfa",
    "timeRemaining":"2 hours and 39 minutes"
  },{
    "membersOnline":6,
    "zoneId":52,
    "groupName":"Hall of Malevolence",
    "timeRemaining":"0 hours and 32 minutes"
  },{
    "membersOnline":6,
    "zoneId":53,
    "groupName":"Hall of Malevolence",
    "timeRemaining":"0 hours and 8 minutes"
  },{
    "membersOnline":2,
    "zoneId":54,
    "groupName":"Ansuzgardaraiwo",
    "timeRemaining":"0 hours and 56 minutes"
  },{
    "membersOnline":10,
    "zoneId":55,
    "groupName":"Seamless Gate",
    "timeRemaining":"3 hours and 8 minutes"
  },{
    "membersOnline":1,
    "zoneId":56,
    "groupName":"sinalfa",
    "timeRemaining":"1 hours and 17 minutes"
  },{
    "membersOnline":1,
    "zoneId":57,
    "groupName":"sinalfa",
    "timeRemaining":"1 hours and 9 minutes"
  },{
    "membersOnline":3,
    "zoneId":58,
    "groupName":"The Cat Family",
    "timeRemaining":"4 hours and 56 minutes"
  },{
    "membersOnline":6,
    "zoneId":59,
    "groupName":"Nightmare Empire",
    "timeRemaining":"0 hours and 40 minutes"
  },{
    "membersOnline":1,
    "zoneId":60,
    "groupName":"sinalfa",
    "timeRemaining":"2 hours and 44 minutes"
  },{
    "membersOnline":1,
    "zoneId":61,
    "groupName":"4FuN",
    "timeRemaining":"0 hours and 24 minutes"
  },{
    "membersOnline":2,
    "zoneId":62,
    "groupName":"Deathsquad",
    "timeRemaining":"0 hours and 24 minutes"
  },{
    "membersOnline":2,
    "zoneId":63,
    "groupName":"Deathsquad",
    "timeRemaining":"0 hours and 24 minutes"
  },{
    "membersOnline":3,
    "zoneId":64,
    "groupName":"The Cat Family",
    "timeRemaining":"4 hours and 56 minutes"
  },{
    "membersOnline":2,
    "zoneId":65,
    "groupName":"<27001a>Cat<37001A>ha<47001A>r<57001A>s<67001A>is Empire",
    "timeRemaining":"4 hours and 49 minutes"
  },{
    "membersOnline":2,
    "zoneId":66,
    "groupName":"Deathsquad",
    "timeRemaining":"0 hours and 25 minutes"
  },{
    "membersOnline":1,
    "zoneId":67,
    "groupName":"Freestyle GunZ",
    "timeRemaining":"4 hours and 57 minutes"
  },{
    "membersOnline":10,
    "zoneId":68,
    "groupName":"Seamless Gate",
    "timeRemaining":"0 hours and 39 minutes"
  },{
    "membersOnline":6,
    "zoneId":69,
    "groupName":"Nightmare Empire",
    "timeRemaining":"3 hours and 24 minutes"
  },{
    "membersOnline":3,
    "zoneId":70,
    "groupName":"The Cat Family",
    "timeRemaining":"1 hours and 33 minutes"
  },{
    "membersOnline":0,
    "zoneId":71,
    "timeRemaining":"0 hours and 18 minutes"
  },{
    "membersOnline":1,
    "zoneId":72,
    "groupName":"4FuN",
    "timeRemaining":"4 hours and 35 minutes"
  },{
    "membersOnline":1,
    "zoneId":73,
    "groupName":"sinalfa",
    "timeRemaining":"1 hours and 16 minutes"
  },{
    "membersOnline":0,
    "zoneId":74,
    "timeRemaining":"4 hours and 13 minutes"
  },{
    "membersOnline":1,
    "zoneId":75,
    "groupName":"4FuN",
    "timeRemaining":"5 hours and 0 minutes"
  },{
    "membersOnline":3,
    "zoneId":76,
    "groupName":"Deathsquad",
    "timeRemaining":"0 hours and 24 minutes"
  },{
    "membersOnline":1,
    "zoneId":77,
    "groupName":"4FuN",
    "timeRemaining":"4 hours and 33 minutes"
  },{
    "membersOnline":10,
    "zoneId":78,
    "groupName":"Seamless Gate",
    "timeRemaining":"3 hours and 6 minutes"
  },{
    "membersOnline":10,
    "zoneId":79,
    "groupName":"Seamless Gate",
    "timeRemaining":"0 hours and 19 minutes"
  },{
    "membersOnline":1,
    "zoneId":80,
    "groupName":"4FuN",
    "timeRemaining":"4 hours and 45 minutes"
  },{
    "membersOnline":1,
    "zoneId":81,
    "groupName":"4FuN",
    "timeRemaining":"0 hours and 24 minutes"
  },{
    "membersOnline":10,
    "zoneId":82,
    "groupName":"Seamless Gate",
    "timeRemaining":"0 hours and 32 minutes"
  },{
    "membersOnline":1,
    "zoneId":83,
    "groupName":"sinalfa",
    "timeRemaining":"2 hours and 46 minutes"
  },{
    "membersOnline":2,
    "zoneId":84,
    "groupName":"Ansuzgardaraiwo",
    "timeRemaining":"0 hours and 29 minutes"
  },{
    "membersOnline":0,
    "zoneId":85,
    "timeRemaining":"4 hours and 35 minutes"
  },{
    "membersOnline":0,
    "zoneId":86,
    "timeRemaining":"4 hours and 36 minutes"
  },{
    "membersOnline":6,
    "zoneId":87,
    "groupName":"Nightmare Empire",
    "timeRemaining":"5 hours and 36 minutes"
  },{
    "membersOnline":10,
    "zoneId":88,
    "groupName":"Seamless Gate",
    "timeRemaining":"0 hours and 23 minutes"
  },{
    "membersOnline":6,
    "zoneId":89,
    "groupName":"Hall of Malevolence",
    "timeRemaining":"0 hours and 53 minutes"
  },{
    "membersOnline":1,
    "zoneId":90,
    "groupName":"Freestyle GunZ",
    "timeRemaining":"4 hours and 53 minutes"
  },{
    "membersOnline":1,
    "zoneId":91,
    "groupName":"Freestyle GunZ",
    "timeRemaining":"3 hours and 32 minutes"
  },{
    "membersOnline":10,
    "zoneId":92,
    "groupName":"Seamless Gate",
    "timeRemaining":"3 hours and 2 minutes"
  },{
    "membersOnline":1,
    "zoneId":93,
    "groupName":"Freestyle GunZ",
    "timeRemaining":"4 hours and 56 minutes"
  },{
    "membersOnline":2,
    "zoneId":94,
    "groupName":"<27001a>Cat<37001A>ha<47001A>r<57001A>s<67001A>is Empire",
    "timeRemaining":"4 hours and 47 minutes"
  },{
    "membersOnline":1,
    "zoneId":95,
    "groupName":"4FuN",
    "timeRemaining":"0 hours and 15 minutes"
  },{
    "membersOnline":10,
    "zoneId":96,
    "groupName":"Seamless Gate",
    "timeRemaining":"0 hours and 10 minutes"
  },{
    "membersOnline":10,
    "zoneId":97,
    "groupName":"Seamless Gate",
    "timeRemaining":"3 hours and 11 minutes"
  },{
    "membersOnline":6,
    "zoneId":98,
    "groupName":"Nightmare Empire",
    "timeRemaining":"2 hours and 35 minutes"
  },{
    "membersOnline":6,
    "zoneId":99,
    "groupName":"Hall of Malevolence",
    "timeRemaining":"0 hours and 9 minutes"
  },{
    "membersOnline":0,
    "zoneId":100,
    "timeRemaining":"0 hours and 22 minutes"
  },{
    "membersOnline":1,
    "zoneId":101,
    "groupName":"4FuN",
    "timeRemaining":"0 hours and 25 minutes"
  },{
    "membersOnline":6,
    "zoneId":102,
    "groupName":"Nightmare Empire",
    "timeRemaining":"3 hours and 31 minutes"
  },{
    "membersOnline":6,
    "zoneId":103,
    "groupName":"Nightmare Empire",
    "timeRemaining":"5 hours and 32 minutes"
  },{
    "membersOnline":6,
    "zoneId":104,
    "groupName":"Hall of Malevolence",
    "timeRemaining":"0 hours and 0 minutes"
  },{
    "membersOnline":3,
    "zoneId":105,
    "groupName":"The Cat Family",
    "timeRemaining":"1 hours and 29 minutes"
  },{
    "membersOnline":3,
    "zoneId":106,
    "groupName":"The Cat Family",
    "timeRemaining":"1 hours and 30 minutes"
  },{
    "membersOnline":1,
    "zoneId":107,
    "groupName":"4FuN",
    "timeRemaining":"0 hours and 20 minutes"
  },{
    "membersOnline":1,
    "zoneId":108,
    "groupName":"sinalfa",
    "timeRemaining":"1 hours and 17 minutes"
  },{
    "membersOnline":10,
    "zoneId":109,
    "groupName":"Seamless Gate",
    "timeRemaining":"5 hours and 4 minutes"
  },{
    "membersOnline":1,
    "zoneId":110,
    "groupName":"sinalfa",
    "timeRemaining":"2 hours and 36 minutes"
  },{
    "membersOnline":3,
    "zoneId":111,
    "groupName":"The Cat Family",
    "timeRemaining":"1 hours and 22 minutes"
  },{
    "membersOnline":1,
    "zoneId":112,
    "groupName":"4FuN",
    "timeRemaining":"0 hours and 21 minutes"
  },{
    "membersOnline":2,
    "zoneId":113,
    "groupName":"Ansuzgardaraiwo",
    "timeRemaining":"0 hours and 42 minutes"
  },{
    "membersOnline":6,
    "zoneId":114,
    "groupName":"Hall of Malevolence",
    "timeRemaining":"0 hours and 10 minutes"
  },{
    "membersOnline":1,
    "zoneId":115,
    "groupName":"Ancient Knowledge Stone ",
    "timeRemaining":"5 hours and 19 minutes"
  },{
    "membersOnline":6,
    "zoneId":116,
    "groupName":"Nightmare Empire",
    "timeRemaining":"0 hours and 35 minutes"
  },{
    "membersOnline":1,
    "zoneId":117,
    "groupName":"4FuN",
    "timeRemaining":"4 hours and 36 minutes"
  },{
    "membersOnline":1,
    "zoneId":118,
    "groupName":"Ancient Knowledge Stone ",
    "timeRemaining":"5 hours and 46 minutes"
  },{
    "membersOnline":3,
    "zoneId":119,
    "groupName":"The Cat Family",
    "timeRemaining":"4 hours and 56 minutes"
  },{
    "membersOnline":0,
    "zoneId":120,
    "timeRemaining":"0 hours and 13 minutes"
  },{
    "membersOnline":6,
    "zoneId":121,
    "groupName":"Nightmare Empire",
    "timeRemaining":"3 hours and 25 minutes"
  }]